Workbook

Sheet Leeme
A1: PCB 2 (OBC + ADCS) - CubeSat UD34 - Práctica 4
A2: Hoja de cálculo de soporte: supuestos, BOM, costos, cálculos, matriz de restricciones, registro ERC y desviaciones.
A3: Integrantes: Juan Pablo González Blandón, Santiago Castaño Loaiza. Altium Designer 26.9.1. Fecha de consulta de precios y proveedor: 27/10/2026.
A5: Hojas
A6: Supuestos: tipo de cambio, tamaños de lote, constantes (celdas amarillas = editables).
A7: Precios: escalones de precio por componente (fuente, moneda, fecha). Fondo naranja = precio ESTIMADO sin cotización.
A8: BOM: lista de materiales del esquemático entregado (as-built).
A9: Costos: costo por lote 10/100/1000 con fórmulas, y costo por tarjeta + gráfica.
A10: Calculos: cristal HSE, pull-ups I2C, ancho de pista (IPC-2221), consumo.
A11: Restricciones: matriz de restricciones de PCB y de fabricación (ID, restricción, fuente, verificación, estado).
A12: ERC: registro de la validación automática y manual, con excepciones aceptadas.
A13: Desviaciones: diferencias entre la especificación/informe previo y el esquemático as-built.
... A19: No incluye fabricación de la PCB, ensamblaje, transporte ni impuestos.

Sheet Supuestos
A1: Parámetro | B1: Valor | C1: Unidad | D1: Fuente / nota
A2: Tarjetas en lote 1 | B2: 10 | C2: uds | D2: Guía Práctica 4, paso 11
A3: Tarjetas en lote 2 | B3: 100 | C3: uds | D3: Guía Práctica 4, paso 11
A4: Tarjetas en lote 3 | B4: 1000 | C4: uds | D4: Guía Práctica 4, paso 11
A5: Tipo de cambio SGD -> USD | B5: 0.77 | C5: USD/SGD | D5: SUPUESTO del equipo (aprox.). Actualizar con la tasa del día de compra.
A6: Tipo de cambio EUR -> USD | B6: 1.08 | C6: USD/EUR | D6: SUPUESTO del equipo (aprox.). Actualizar con la tasa del día de compra.
A7: Fecha de consulta de precios | B7: 27/10/2026 | D7: Precios de referencia; cambian a diario

Sheet Precios
A1: Clave | B1: Componente (MPN) | C1: Moneda origen | D1: Factor a USD | E1: Q1 | F1: Q2 | G1: Q3 | H1: Q4 | I1: Q5 | J1: Q6 | K1: Q7 | L1: P1 | M1: P2 | N1: P3 | O1: P4 | P1: P5 | Q1: P6 | R1: P7 | S1: Estado | T1: Fuente (fecha 27/10/2026)
A2: STM32 | B2: STM32H753IIT6 | C2: USD | D2: 1 | E2: 1 | F2: 10 | G2: 30 | H2: 100 | I2: 1000000 | J2: 2000000 | K2: 3000000 | L2: 9.2873 | M2: 8.0151 | N2: 7.2387 | O2: 6.587 | P2: 6.587 | Q2: 6.587 | R2: 6.587 | S2: Cotizado | T2: LCSC C146558 (https://www.lcsc.com/product-image/C146558.html). Referencia; DigiKey/TME muestran 0 o poco stock.
A3: EMMC | B3: EMMC04G-M627-A01 (Kingston) | C3: USD | D3: 1 | E3: 1 | F3: 10 | G3: 30 | H3: 152 | I3: 456 | J3: 1064 | K3: 1976 | L3: 5.3178 | M3: 4.6209 | N3: 4.2064 | O3: 3.7873 | P3: 3.5938 | Q3: 3.5063 | R3: 3.468 | S3: Cotizado (sin stock) | T3: LCSC C577446 (https://www.lcsc.com/product-image/C577446.html). Aparece sin stock: disponibilidad PENDIENTE.
A4: SDRAM | B4: MT48LC4M16A2P-6A (Micron) | C4: EUR | D4: =Supuestos!$B$6 -> 1.08 | E4: 1 | F4: 1000000 | G4: 2000000 | H4: 3000000 | I4: 4000000 | J4: 5000000 | K4: 6000000 | L4: 4.52 | M4: 4.52 | N4: 4.52 | O4: 4.52 | P4: 4.52 | Q4: 4.52 | R4: 4.52 | S4: ESTIMADO | T4: DigiKey ES MT48LC4M16A2P-6A IT:J TR, 4,52 EUR sin IVA, un solo escalón visible (https://www.digikey.com/en/products/detail/micron-technology-inc/MT48LC4M16A2P-6A-IT-J-TR/4315481). Estado 'Last Time Buy' (fecha 30/06/2026 ya vencida): disponibilidad PENDIENTE; se aplica el mismo precio a los 3 lotes.
A5: ISO | B5: ISO7741DWR (TI) | C5: USD | D5: 1 | E5: 1 | F5: 10 | G5: 30 | H5: 100 | I5: 500 | J5: 1000 | K5: 1000000 | L5: 1.0689 | M5: 0.8819 | N5: 0.7803 | O5: 0.6642 | P5: 0.6126 | Q5: 0.5901 | R5: 0.5901 | S5: Cotizado | T5: LCSC C571196 (https://www.lcsc.com/product-image/C571196.html). Otros distribuidores muestran precios mayores (p.ej. 2,57 EUR en DigiKey DE sin stock).
A6: DRV | B6: DRV8833PWPR (TI) | C6: USD | D6: 1 | E6: 1 | F6: 10 | G6: 30 | H6: 100 | I6: 500 | J6: 1000 | K6: 1000000 | L6: 0.6751 | M6: 0.5379 | N6: 0.4692 | O6: 0.4006 | P6: 0.3735 | Q6: 0.3511 | R6: 0.3511 | S6: Cotizado | T6: LCSC C50506 (https://www.lcsc.com/product-image/C50506.html). DigiKey/Mouser muestran 1,68-2,34 USD.
A7: XTAL | B7: ABM3B-25.000MHZ-B4U-T (Abracon) | C7: USD | D7: 1 | E7: 1 | F7: 10 | G7: 30 | H7: 100 | I7: 1000000 | J7: 2000000 | K7: 3000000 | L7: 0.6966 | M7: 0.5644 | N7: 0.4983 | O7: 0.4321 | P7: 0.4321 | Q7: 0.4321 | R7: 0.4321 | S7: ESTIMADO (variante) | T7: Sin cotización de la referencia exacta. Se usa como proxy la variante ABM3B-25.000MHZ-B2-T en LCSC C596875 (https://www.lcsc.com/product-image/C596875.html).
A8: C100N | B8: GRM155R71C104KA88D (Murata) 0,1 uF 0402 | C8: USD | D8: 1 | E8: 1 | F8: 10 | G8: 50 | H8: 100 | I8: 500 | J8: 1000 | K8: 5000 | L8: 0.1 | M8: 0.024 | N8: 0.0156 | O8: 0.0132 | P8: 0.0093 | Q8: 0.008 | R8: 0.006 | S8: Cotizado | T8: DigiKey 490-3261-1-ND vía OEMsTrade (https://www.oemstrade.com/search/grm155r71c104ka88d%200402-104k%20pb-free).
A9: R10K | B9: ERJ3EKF1002V (Panasonic) 10 kOhm 0603 | C9: USD | D9: 1 | E9: 1 | F9: 10 | G9: 25 | H9: 1000000 | I9: 2000000 | J9: 3000000 | K9: 4000000 | L9: 0.1 | M9: 0.034 | N9: 0.0256 | O9: 0.0256 | P9: 0.0256 | Q9: 0.0256 | R9: 0.0256 | S9: Cotizado | T9: DigiKey P10.0KHCT-ND (https://www.digikey.com/en/products/detail/panasonic-electronic-components/ERJ-3EKF1002V/196066). Solo se ven 3 escalones; se mantiene el último.
A10: R_GEN | B10: Resistencias 33 ohm / 4,7 kohm 0603 1 % | C10: USD | D10: 1 | E10: 1 | F10: 10 | G10: 25 | H10: 1000000 | I10: 2000000 | J10: 3000000 | K10: 4000000 | L10: 0.1 | M10: 0.034 | N10: 0.0256 | O10: 0.0256 | P10: 0.0256 | Q10: 0.0256 | R10: 0.0256 | S10: ESTIMADO (proxy) | T10: Sin cotización de la referencia exacta; se usa el precio de la serie ERJ3EKF (ERJ3EKF1002V).
A11: C_PF | B11: Condensador 16 pF C0G 0402 | C11: USD | D11: 1 | E11: 1 | F11: 100 | G11: 1000 | H11: 1000000 | I11: 2000000 | J11: 3000000 | K11: 4000000 | L11: 0.05 | M11: 0.02 | N11: 0.012 | O11: 0.012 | P11: 0.012 | Q11: 0.012 | R11: 0.012 | S11: ESTIMADO | T11: Sin cotización. Estimación del equipo; reemplazar al definir la referencia exacta.
A12: C_2U2 | B12: Condensador 2,2 uF (VCAP) | C12: USD | D12: 1 | E12: 1 | F12: 100 | G12: 1000 | H12: 1000000 | I12: 2000000 | J12: 3000000 | K12: 4000000 | L12: 0.1 | M12: 0.05 | N12: 0.03 | O12: 0.03 | P12: 0.03 | Q12: 0.03 | R12: 0.03 | S12: ESTIMADO | T12: Sin cotización. Estimación del equipo; reemplazar al definir la referencia exacta.
A13: C_10U | B13: Condensador 10 uF | C13: USD | D13: 1 | E13: 1 | F13: 100 | G13: 1000 | H13: 1000000 | I13: 2000000 | J13: 3000000 | K13: 4000000 | L13: 0.15 | M13: 0.08 | N13: 0.05 | O13: 0.05 | P13: 0.05 | Q13: 0.05 | R13: 0.05 | S13: ESTIMADO | T13: Sin cotización. Estimación del equipo; reemplazar al definir la referencia exacta.
A14: J_SWD | B14: Molex 53259-0429 (4 pines, 3,5 mm) | C14: SGD | D14: =Supuestos!$B$5 -> 0.77 | E14: 1 | F14: 10 | G14: 50 | H14: 250 | I14: 750 | J14: 2250 | K14: 1000000 | L14: 0.967 | M14: 0.967 | N14: 0.964 | O14: 0.95 | P14: 0.906 | Q14: 0.782 | R14: 0.782 | S14: Cotizado (RS, SGD) | T14: RS 602-1299, paquete de 10 (https://sg.rs-online.com/web/p/pcb-headers/6021299). Escalones 10-40, 50-240, 250-740, 750-2240, 2250+.
A15: HDR_PIN | B15: Cabecera genérica, precio por pin | C15: USD | D15: 1 | E15: 1 | F15: 100 | G15: 1000 | H15: 1000000 | I15: 2000000 | J15: 3000000 | K15: 4000000 | L15: 0.08 | M15: 0.05 | N15: 0.03 | O15: 0.03 | P15: 0.03 | Q15: 0.03 | R15: 0.03 | S15: ESTIMADO | T15: Los conectores J_EPS, J_COIL_X/Y, J_PAYLOAD, J_CAMERA y J_TELEM son símbolos genéricos sin referencia comercial; se estima por pin.

Sheet BOM
A1: Línea | B1: Designadores | C1: Descripción | D1: Cant./tarjeta | E1: Fabricante | F1: Referencia exacta (MPN) | G1: Encapsulado / huella | H1: Hoja esquemática | I1: Estado de montaje | J1: Clave de precio | K1: Pines (solo cabeceras) | L1: Observaciones
A2: 1 | B2: U1 | C2: Microcontrolador ARM Cortex-M7 480 MHz, 2 MB Flash | D2: 1 | E2: STMicroelectronics | F2: STM32H753IIT6 | G2: LQFP-176 (24x24) | H2: U_OBC_Core | I2: Montado | J2: STM32 | L2: Símbolo en 3 partes (U1A/U1B/U1C).
A3: 2 | B3: *1 | C3: eMMC 4 GB | D3: 1 | E3: Kingston | F3: EMMC04G-M627-A01 | G3: FBGA-153 | H3: U_Mass_Storage | I3: Montado | J3: EMMC | L3: Designador *1 tras anotar. VCC y VCCQ a 3V3_DIGITAL (el informe previo decía VCCQ 1,8 V).
A4: 3 | B4: U2 | C4: SDRAM 64 Mbit (4M x 16), 3,3 V | D4: 1 | E4: Micron | F4: MT48LC4M16A2P-6A | G4: TSOP-II 54 | H4: U_Mass_Storage | I4: Montado | J4: SDRAM | L4: Estado Last Time Buy en DigiKey (30/06/2026).
A5: 4 | B5: U3 | C5: Aislador digital 4 canales (3 + 1), 5 kVrms | D5: 1 | E5: Texas Instruments | F5: ISO7741DWR | G5: SOIC-16 DW | H5: U_ADCS_Isolated | I5: Montado | J5: ISO | L5: Solo 3 canales en el mismo sentido: PWM_B2 queda sin conexión.
A6: 5 | B6: U4 | C6: Puente H doble 2,7-10,8 V | D6: 1 | E6: Texas Instruments | F6: DRV8833PWPR | G6: HTSSOP-16 (PowerPAD) | H6: U_ADCS_Isolated | I6: Montado | J6: DRV
A7: 6 | B7: Y1 | C7: Cristal 25 MHz (HSE) | D7: 1 | E7: Abracon | F7: ABM3B-25.000MHZ-B4U-T | G7: SMD 5,0 x 3,2 mm, 4 pines | H7: U_OBC_Core | I7: Montado | J7: XTAL | L7: Capacitancia de carga a verificar con la hoja de datos (ver Calculos).
A8: 7 | B8: C1, C6 | C8: Condensador cerámico 0,1 uF X7R 16 V | D8: 2 | E8: Murata | F8: GRM155R71C104KA88D | G8: 0402 | H8: U_OBC_Core (C1), U_Interfaces_Connectors (C6) | I8: Montado | J8: C100N | L8: C1 en SYS_RESET; C6 en J_EPS.
A9: 8 | B9: R1 | C9: Resistencia 10 kOhm 1 % 0603 | D9: 1 | E9: Panasonic | F9: ERJ3EKF1002V | G9: 0603 | H9: U_OBC_Core | I9: Montado | J9: R10K | L9: Pull-down de BOOT0.
A10: 9 | B10: R6, R7 | C10: Resistencia 4,7 kOhm 0603 | D10: 2 | E10: Panasonic (a definir) | F10: Serie ERJ3EKF (valor 4,7 kOhm, MPN por confirmar) | G10: 0603 | H10: U_OBC_Core | I10: Montado | J10: R_GEN | L10: Pull-ups I2C.
A11: 10 | B11: R2, R3, R4, R5 | C11: Resistencia serie 33 ohm 0603 | D11: 4 | E11: Panasonic (a definir) | F11: Serie ERJ3EKF (valor 33 ohm, MPN por confirmar) | G11: 0603 | H11: U_OBC_Core | I11: Montado | J11: R_GEN | L11: Terminación serie SPI (NSS, SCK, MISO, MOSI).
A12: 11 | B12: C2, C5 | C12: Condensador 16 pF C0G (carga del cristal) | D12: 2 | E12: A definir | F12: Por confirmar | G12: 0402 (a verificar) | H12: U_OBC_Core | I12: Montado | J12: C_PF | L12: Valor a revisar frente a la capacitancia de carga del cristal.
A13: 12 | B13: C3, C4 | C13: Condensador 2,2 uF (VCAP del STM32) | D13: 2 | E13: A definir | F13: Por confirmar | G13: 0603 (a verificar) | H13: U_OBC_Core | I13: Montado | J13: C_2U2 | L13: Condensadores VCAP1/VCAP2.
A14: 13 | B14: C7 | C14: Condensador 10 uF (filtrado J_EPS) | D14: 1 | E14: A definir | F14: Por confirmar | G14: 0805 (a verificar) | H14: U_Interfaces_Connectors | I14: Montado | J14: C_10U
A15: 14 | B15: J1 | C15: Cabecera 4 pines 3,5 mm SWD | D15: 1 | E15: Molex | F15: 53259-0429 | G15: THT acodada 3,5 mm | H15: U_OBC_Core | I15: Montado | J15: J_SWD | L15: Conector de depuración SWD (3V3, SWCLK, SWDIO, DGND).
A16: 15 | B16: J2 (J_EPS) | C16: Cabecera 3 pines (potencia EPS) | D16: 1 | E16: Genérico | F16: Sin referencia comercial | G16: Cabecera 3 pines | H16: U_Interfaces_Connectors | I16: Montado | J16: HDR_PIN | K16: 3 | L16: Solo MAIN_BUS_POWER, 3V3_DIGITAL y DGND.
A17: 16 | B17: J3 (J_COIL_X) | C17: Cabecera 2 pines (bobina X) | D17: 1 | E17: Genérico | F17: Sin referencia comercial | G17: Cabecera 2 pines | H17: U_Interfaces_Connectors | I17: Montado | J17: HDR_PIN | K17: 2
A18: 17 | B18: J4 (J_COIL_Y) | C18: Cabecera 2 pines (bobina Y) | D18: 1 | E18: Genérico | F18: Sin referencia comercial | G18: Cabecera 2 pines | H18: U_Interfaces_Connectors | I18: Montado | J18: HDR_PIN | K18: 2
A19: 18 | B19: P1 (J_PAYLOAD) | C19: Cabecera 5 pines (SPI + DGND) | D19: 1 | E19: Genérico | F19: Sin referencia comercial | G19: Cabecera 5 pines | H19: U_Interfaces_Connectors | I19: Montado | J19: HDR_PIN | K19: 5
A20: 19 | B20: P2 (J_CAMERA) | C20: Cabecera 16 pines (DCMI + I2C + 3V3 + DGND) | D20: 1 | E20: Genérico | F20: Sin referencia comercial | G20: Cabecera 16 pines | H20: U_Interfaces_Connectors | I20: Montado | J20: HDR_PIN | K20: 16
A21: 20 | B21: P3 (J_TELEM) | C21: Cabecera 4 pines (I2C + 3V3 + DGND) | D21: 1 | E21: Genérico | F21: Sin referencia comercial | G21: Cabecera 4 pines | H21: U_Interfaces_Connectors | I21: Montado | J21: HDR_PIN | K21: 4
A23: Componentes opcionales o no montados: ninguno. Configuración usada para el costo: todos los componentes de esta lista montados.
A24: Total de componentes por tarjeta (unidades): | F24: =SUM(D2:D21) -> 27

Sheet Costos
A1: Línea BOM | B1: Designadores | C1: Clave | D1: Cant./tarjeta (piezas) | E1: Piezas lote 1 | F1: Piezas lote 2 | G1: Piezas lote 3 | H1: Precio unit. USD lote 1 | I1: Precio unit. USD lote 2 | J1: Precio unit. USD lote 3 | K1: Costo USD lote 1 | L1: Costo USD lote 2 | M1: Costo USD lote 3 | N1: Estado del precio
A2: =BOM!A2 -> 1 | B2: =BOM!B2 -> U1 | C2: =BOM!J2 -> STM32 | D2: =IF(BOM!K2="",BOM!D2,BOM!D2*BOM!K2) -> 1 | E2: =D2*Supuestos!$B$2 -> 10 | F2: =D2*Supuestos!$B$3 -> 100 | G2: =D2*Supuestos!$B$4 -> 1000 | H2: =IFERROR(INDEX(Precios!$L$2:$R$100,MATCH($C2,Precios!$A$2:$A$100,0),MATCH(E2,INDEX(Precios!$E$2:$K$100,MATCH($C2,Precios!$A$2:$A$100,0),0),1))*INDEX(Precios!$D$2:$D$100,MATCH($C2,Precios!$A$2:$A$100,0)),INDEX(Precios!$L$2:$L$100,MATCH($C2,Precios!$A$2:$A$100,0))*INDEX(Precios!$D$2:$D$100,MATCH($C2,Precios!$A$2:$A$100,0))) -> 8.0151 | I2: =IFERROR(INDEX(Precios!$L$2:$R$100,MATCH($C2,Precios!$A$2:$A$100,0),MATCH(F2,INDEX(Precios!$E$2:$K$100,MATCH($C2,Precios!$A$2:$A$100,0),0),1))*INDEX(Precios!$D$2:$D$100,MATCH($C2,Precios!$A$2:$A$100,0)),INDEX(Precios!$L$2:$L$100,MATCH($C2,Precios!$A$2:$A$100,0))*INDEX(Precios!$D$2:$D$100,MATCH($C2,Precios!$A$2:$A$100,0))) -> 6.587 | J2: =IFERROR(INDEX(Precios!$L$2:$R$100,MATCH($C2,Precios!$A$2:$A$100,0),MATCH(G2,INDEX(Precios!$E$2:$K$100,MATCH($C2,Precios!$A$2:$A$100,0),0),1))*INDEX(Precios!$D$2:$D$100,MATCH($C2,Precios!$A$2:$A$100,0)),INDEX(Precios!$L$2:$L$100,MATCH($C2,Precios!$A$2:$A$100,0))*INDEX(Precios!$D$2:$D$100,MATCH($C2,Precios!$A$2:$A$100,0))) -> 6.587 | K2: =E2*H2 -> 80.151 | L2: =F2*I2 -> 658.7 | M2: =G2*J2 -> 6587 | N2: =INDEX(Precios!$S$2:$S$100,MATCH($C2,Precios!$A$2:$A$100,0)) -> Cotizado
A3: =BOM!A3 -> 2 | B3: =BOM!B3 -> *1 | C3: =BOM!J3 -> EMMC | D3: =IF(BOM!K3="",BOM!D3,BOM!D3*BOM!K3) -> 1 | E3: =D3*Supuestos!$B$2 -> 10 | F3: =D3*Supuestos!$B$3 -> 100 | G3: =D3*Supuestos!$B$4 -> 1000 | H3: =IFERROR(INDEX(Precios!$L$2:$R$100,MATCH($C3,Precios!$A$2:$A$100,0),MATCH(E3,INDEX(Precios!$E$2:$K$100,MATCH($C3,Precios!$A$2:$A$100,0),0),1))*INDEX(Precios!$D$2:$D$100,MATCH($C3,Precios!$A$2:$A$100,0)),INDEX(Precios!$L$2:$L$100,MATCH($C3,Precios!$A$2:$A$100,0))*INDEX(Precios!$D$2:$D$100,MATCH($C3,Precios!$A$2:$A$100,0))) -> 4.6209 | I3: =IFERROR(INDEX(Precios!$L$2:$R$100,MATCH($C3,Precios!$A$2:$A$100,0),MATCH(F3,INDEX(Precios!$E$2:$K$100,MATCH($C3,Precios!$A$2:$A$100,0),0),1))*INDEX(Precios!$D$2:$D$100,MATCH($C3,Precios!$A$2:$A$100,0)),INDEX(Precios!$L$2:$L$100,MATCH($C3,Precios!$A$2:$A$100,0))*INDEX(Precios!$D$2:$D$100,MATCH($C3,Precios!$A$2:$A$100,0))) -> 4.2064 | J3: =IFERROR(INDEX(Precios!$L$2:$R$100,MATCH($C3,Precios!$A$2:$A$100,0),MATCH(G3,INDEX(Precios!$E$2:$K$100,MATCH($C3,Precios!$A$2:$A$100,0),0),1))*INDEX(Precios!$D$2:$D$100,MATCH($C3,Precios!$A$2:$A$100,0)),INDEX(Precios!$L$2:$L$100,MATCH($C3,Precios!$A$2:$A$100,0))*INDEX(Precios!$D$2:$D$100,MATCH($C3,Precios!$A$2:$A$100,0))) -> 3.5938 | K3: =E3*H3 -> 46.209 | L3: =F3*I3 -> 420.64 | M3: =G3*J3 -> 3593.8 | N3: =INDEX(Precios!$S$2:$S$100,MATCH($C3,Precios!$A$2:$A$100,0)) -> Cotizado (sin stock)
A4: =BOM!A4 -> 3 | B4: =BOM!B4 -> U2 | C4: =BOM!J4 -> SDRAM | D4: =IF(BOM!K4="",BOM!D4,BOM!D4*BOM!K4) -> 1 | E4: =D4*Supuestos!$B$2 -> 10 | F4: =D4*Supuestos!$B$3 -> 100 | G4: =D4*Supuestos!$B$4 -> 1000 | H4: =IFERROR(INDEX(Precios!$L$2:$R$100,MATCH($C4,Precios!$A$2:$A$100,0),MATCH(E4,INDEX(Precios!$E$2:$K$100,MATCH($C4,Precios!$A$2:$A$100,0),0),1))*INDEX(Precios!$D$2:$D$100,MATCH($C4,Precios!$A$2:$A$100,0)),INDEX(Precios!$L$2:$L$100,MATCH($C4,Precios!$A$2:$A$100,0))*INDEX(Precios!$D$2:$D$100,MATCH($C4,Precios!$A$2:$A$100,0))) -> 4.8816 | I4: =IFERROR(INDEX(Precios!$L$2:$R$100,MATCH($C4,Precios!$A$2:$A$100,0),MATCH(F4,INDEX(Precios!$E$2:$K$100,MATCH($C4,Precios!$A$2:$A$100,0),0),1))*INDEX(Precios!$D$2:$D$100,MATCH($C4,Precios!$A$2:$A$100,0)),INDEX(Precios!$L$2:$L$100,MATCH($C4,Precios!$A$2:$A$100,0))*INDEX(Precios!$D$2:$D$100,MATCH($C4,Precios!$A$2:$A$100,0))) -> 4.8816 | J4: =IFERROR(INDEX(Precios!$L$2:$R$100,MATCH($C4,Precios!$A$2:$A$100,0),MATCH(G4,INDEX(Precios!$E$2:$K$100,MATCH($C4,Precios!$A$2:$A$100,0),0),1))*INDEX(Precios!$D$2:$D$100,MATCH($C4,Precios!$A$2:$A$100,0)),INDEX(Precios!$L$2:$L$100,MATCH($C4,Precios!$A$2:$A$100,0))*INDEX(Precios!$D$2:$D$100,MATCH($C4,Precios!$A$2:$A$100,0))) -> 4.8816 | K4: =E4*H4 -> 48.816 | L4: =F4*I4 -> 488.16 | M4: =G4*J4 -> 4881.6 | N4: =INDEX(Precios!$S$2:$S$100,MATCH($C4,Precios!$A$2:$A$100,0)) -> ESTIMADO
A5: =BOM!A5 -> 4 | B5: =BOM!B5 -> U3 | C5: =BOM!J5 -> ISO | D5: =IF(BOM!K5="",BOM!D5,BOM!D5*BOM!K5) -> 1 | E5: =D5*Supuestos!$B$2 -> 10 | F5: =D5*Supuestos!$B$3 -> 100 | G5: =D5*Supuestos!$B$4 -> 1000 | H5: =IFERROR(INDEX(Precios!$L$2:$R$100,MATCH($C5,Precios!$A$2:$A$100,0),MATCH(E5,INDEX(Precios!$E$2:$K$100,MATCH($C5,Precios!$A$2:$A$100,0),0),1))*INDEX(Precios!$D$2:$D$100,MATCH($C5,Precios!$A$2:$A$100,0)),INDEX(Precios!$L$2:$L$100,MATCH($C5,Precios!$A$2:$A$100,0))*INDEX(Precios!$D$2:$D$100,MATCH($C5,Precios!$A$2:$A$100,0))) -> 0.8819 | I5: =IFERROR(INDEX(Precios!$L$2:$R$100,MATCH($C5,Precios!$A$2:$A$100,0),MATCH(F5,INDEX(Precios!$E$2:$K$100,MATCH($C5,Precios!$A$2:$A$100,0),0),1))*INDEX(Precios!$D$2:$D$100,MATCH($C5,Precios!$A$2:$A$100,0)),INDEX(Precios!$L$2:$L$100,MATCH($C5,Precios!$A$2:$A$100,0))*INDEX(Precios!$D$2:$D$100,MATCH($C5,Precios!$A$2:$A$100,0))) -> 0.6642 | J5: =IFERROR(INDEX(Precios!$L$2:$R$100,MATCH($C5,Precios!$A$2:$A$100,0),MATCH(G5,INDEX(Precios!$E$2:$K$100,MATCH($C5,Precios!$A$2:$A$100,0),0),1))*INDEX(Precios!$D$2:$D$100,MATCH($C5,Precios!$A$2:$A$100,0)),INDEX(Precios!$L$2:$L$100,MATCH($C5,Precios!$A$2:$A$100,0))*INDEX(Precios!$D$2:$D$100,MATCH($C5,Precios!$A$2:$A$100,0))) -> 0.5901 | K5: =E5*H5 -> 8.819 | L5: =F5*I5 -> 66.42 | M5: =G5*J5 -> 590.1 | N5: =INDEX(Precios!$S$2:$S$100,MATCH($C5,Precios!$A$2:$A$100,0)) -> Cotizado
A6: =BOM!A6 -> 5 | B6: =BOM!B6 -> U4 | C6: =BOM!J6 -> DRV | D6: =IF(BOM!K6="",BOM!D6,BOM!D6*BOM!K6) -> 1 | E6: =D6*Supuestos!$B$2 -> 10 | F6: =D6*Supuestos!$B$3 -> 100 | G6: =D6*Supuestos!$B$4 -> 1000 | H6: =IFERROR(INDEX(Precios!$L$2:$R$100,MATCH($C6,Precios!$A$2:$A$100,0),MATCH(E6,INDEX(Precios!$E$2:$K$100,MATCH($C6,Precios!$A$2:$A$100,0),0),1))*INDEX(Precios!$D$2:$D$100,MATCH($C6,Precios!$A$2:$A$100,0)),INDEX(Precios!$L$2:$L$100,MATCH($C6,Precios!$A$2:$A$100,0))*INDEX(Precios!$D$2:$D$100,MATCH($C6,Precios!$A$2:$A$100,0))) -> 0.5379 | I6: =IFERROR(INDEX(Precios!$L$2:$R$100,MATCH($C6,Precios!$A$2:$A$100,0),MATCH(F6,INDEX(Precios!$E$2:$K$100,MATCH($C6,Precios!$A$2:$A$100,0),0),1))*INDEX(Precios!$D$2:$D$100,MATCH($C6,Precios!$A$2:$A$100,0)),INDEX(Precios!$L$2:$L$100,MATCH($C6,Precios!$A$2:$A$100,0))*INDEX(Precios!$D$2:$D$100,MATCH($C6,Precios!$A$2:$A$100,0))) -> 0.4006 | J6: =IFERROR(INDEX(Precios!$L$2:$R$100,MATCH($C6,Precios!$A$2:$A$100,0),MATCH(G6,INDEX(Precios!$E$2:$K$100,MATCH($C6,Precios!$A$2:$A$100,0),0),1))*INDEX(Precios!$D$2:$D$100,MATCH($C6,Precios!$A$2:$A$100,0)),INDEX(Precios!$L$2:$L$100,MATCH($C6,Precios!$A$2:$A$100,0))*INDEX(Precios!$D$2:$D$100,MATCH($C6,Precios!$A$2:$A$100,0))) -> 0.3511 | K6: =E6*H6 -> 5.379 | L6: =F6*I6 -> 40.06 | M6: =G6*J6 -> 351.1 | N6: =INDEX(Precios!$S$2:$S$100,MATCH($C6,Precios!$A$2:$A$100,0)) -> Cotizado
A7: =BOM!A7 -> 6 | B7: =BOM!B7 -> Y1 | C7: =BOM!J7 -> XTAL | D7: =IF(BOM!K7="",BOM!D7,BOM!D7*BOM!K7) -> 1 | E7: =D7*Supuestos!$B$2 -> 10 | F7: =D7*Supuestos!$B$3 -> 100 | G7: =D7*Supuestos!$B$4 -> 1000 | H7: =IFERROR(INDEX(Precios!$L$2:$R$100,MATCH($C7,Precios!$A$2:$A$100,0),MATCH(E7,INDEX(Precios!$E$2:$K$100,MATCH($C7,Precios!$A$2:$A$100,0),0),1))*INDEX(Precios!$D$2:$D$100,MATCH($C7,Precios!$A$2:$A$100,0)),INDEX(Precios!$L$2:$L$100,MATCH($C7,Precios!$A$2:$A$100,0))*INDEX(Precios!$D$2:$D$100,MATCH($C7,Precios!$A$2:$A$100,0))) -> 0.5644 | I7: =IFERROR(INDEX(Precios!$L$2:$R$100,MATCH($C7,Precios!$A$2:$A$100,0),MATCH(F7,INDEX(Precios!$E$2:$K$100,MATCH($C7,Precios!$A$2:$A$100,0),0),1))*INDEX(Precios!$D$2:$D$100,MATCH($C7,Precios!$A$2:$A$100,0)),INDEX(Precios!$L$2:$L$100,MATCH($C7,Precios!$A$2:$A$100,0))*INDEX(Precios!$D$2:$D$100,MATCH($C7,Precios!$A$2:$A$100,0))) -> 0.4321 | J7: =IFERROR(INDEX(Precios!$L$2:$R$100,MATCH($C7,Precios!$A$2:$A$100,0),MATCH(G7,INDEX(Precios!$E$2:$K$100,MATCH($C7,Precios!$A$2:$A$100,0),0),1))*INDEX(Precios!$D$2:$D$100,MATCH($C7,Precios!$A$2:$A$100,0)),INDEX(Precios!$L$2:$L$100,MATCH($C7,Precios!$A$2:$A$100,0))*INDEX(Precios!$D$2:$D$100,MATCH($C7,Precios!$A$2:$A$100,0))) -> 0.4321 | K7: =E7*H7 -> 5.644 | L7: =F7*I7 -> 43.21 | M7: =G7*J7 -> 432.1 | N7: =INDEX(Precios!$S$2:$S$100,MATCH($C7,Precios!$A$2:$A$100,0)) -> ESTIMADO (variante)
A8: =BOM!A8 -> 7 | B8: =BOM!B8 -> C1, C6 | C8: =BOM!J8 -> C100N | D8: =IF(BOM!K8="",BOM!D8,BOM!D8*BOM!K8) -> 2 | E8: =D8*Supuestos!$B$2 -> 20 | F8: =D8*Supuestos!$B$3 -> 200 | G8: =D8*Supuestos!$B$4 -> 2000 | H8: =IFERROR(INDEX(Precios!$L$2:$R$100,MATCH($C8,Precios!$A$2:$A$100,0),MATCH(E8,INDEX(Precios!$E$2:$K$100,MATCH($C8,Precios!$A$2:$A$100,0),0),1))*INDEX(Precios!$D$2:$D$100,MATCH($C8,Precios!$A$2:$A$100,0)),INDEX(Precios!$L$2:$L$100,MATCH($C8,Precios!$A$2:$A$100,0))*INDEX(Precios!$D$2:$D$100,MATCH($C8,Precios!$A$2:$A$100,0))) -> 0.024 | I8: =IFERROR(INDEX(Precios!$L$2:$R$100,MATCH($C8,Precios!$A$2:$A$100,0),MATCH(F8,INDEX(Precios!$E$2:$K$100,MATCH($C8,Precios!$A$2:$A$100,0),0),1))*INDEX(Precios!$D$2:$D$100,MATCH($C8,Precios!$A$2:$A$100,0)),INDEX(Precios!$L$2:$L$100,MATCH($C8,Precios!$A$2:$A$100,0))*INDEX(Precios!$D$2:$D$100,MATCH($C8,Precios!$A$2:$A$100,0))) -> 0.0132 | J8: =IFERROR(INDEX(Precios!$L$2:$R$100,MATCH($C8,Precios!$A$2:$A$100,0),MATCH(G8,INDEX(Precios!$E$2:$K$100,MATCH($C8,Precios!$A$2:$A$100,0),0),1))*INDEX(Precios!$D$2:$D$100,MATCH($C8,Precios!$A$2:$A$100,0)),INDEX(Precios!$L$2:$L$100,MATCH($C8,Precios!$A$2:$A$100,0))*INDEX(Precios!$D$2:$D$100,MATCH($C8,Precios!$A$2:$A$100,0))) -> 0.008 | K8: =E8*H8 -> 0.48 | L8: =F8*I8 -> 2.64 | M8: =G8*J8 -> 16 | N8: =INDEX(Precios!$S$2:$S$100,MATCH($C8,Precios!$A$2:$A$100,0)) -> Cotizado
A9: =BOM!A9 -> 8 | B9: =BOM!B9 -> R1 | C9: =BOM!J9 -> R10K | D9: =IF(BOM!K9="",BOM!D9,BOM!D9*BOM!K9) -> 1 | E9: =D9*Supuestos!$B$2 -> 10 | F9: =D9*Supuestos!$B$3 -> 100 | G9: =D9*Supuestos!$B$4 -> 1000 | H9: =IFERROR(INDEX(Precios!$L$2:$R$100,MATCH($C9,Precios!$A$2:$A$100,0),MATCH(E9,INDEX(Precios!$E$2:$K$100,MATCH($C9,Precios!$A$2:$A$100,0),0),1))*INDEX(Precios!$D$2:$D$100,MATCH($C9,Precios!$A$2:$A$100,0)),INDEX(Precios!$L$2:$L$100,MATCH($C9,Precios!$A$2:$A$100,0))*INDEX(Precios!$D$2:$D$100,MATCH($C9,Precios!$A$2:$A$100,0))) -> 0.034 | I9: =IFERROR(INDEX(Precios!$L$2:$R$100,MATCH($C9,Precios!$A$2:$A$100,0),MATCH(F9,INDEX(Precios!$E$2:$K$100,MATCH($C9,Precios!$A$2:$A$100,0),0),1))*INDEX(Precios!$D$2:$D$100,MATCH($C9,Precios!$A$2:$A$100,0)),INDEX(Precios!$L$2:$L$100,MATCH($C9,Precios!$A$2:$A$100,0))*INDEX(Precios!$D$2:$D$100,MATCH($C9,Precios!$A$2:$A$100,0))) -> 0.0256 | J9: =IFERROR(INDEX(Precios!$L$2:$R$100,MATCH($C9,Precios!$A$2:$A$100,0),MATCH(G9,INDEX(Precios!$E$2:$K$100,MATCH($C9,Precios!$A$2:$A$100,0),0),1))*INDEX(Precios!$D$2:$D$100,MATCH($C9,Precios!$A$2:$A$100,0)),INDEX(Precios!$L$2:$L$100,MATCH($C9,Precios!$A$2:$A$100,0))*INDEX(Precios!$D$2:$D$100,MATCH($C9,Precios!$A$2:$A$100,0))) -> 0.0256 | K9: =E9*H9 -> 0.34 | L9: =F9*I9 -> 2.56 | M9: =G9*J9 -> 25.6 | N9: =INDEX(Precios!$S$2:$S$100,MATCH($C9,Precios!$A$2:$A$100,0)) -> Cotizado
A10: =BOM!A10 -> 9 | B10: =BOM!B10 -> R6, R7 | C10: =BOM!J10 -> R_GEN | D10: =IF(BOM!K10="",BOM!D10,BOM!D10*BOM!K10) -> 2 | E10: =D10*Supuestos!$B$2 -> 20 | F10: =D10*Supuestos!$B$3 -> 200 | G10: =D10*Supuestos!$B$4 -> 2000 | H10: =IFERROR(INDEX(Precios!$L$2:$R$100,MATCH($C10,Precios!$A$2:$A$100,0),MATCH(E10,INDEX(Precios!$E$2:$K$100,MATCH($C10,Precios!$A$2:$A$100,0),0),1))*INDEX(Precios!$D$2:$D$100,MATCH($C10,Precios!$A$2:$A$100,0)),INDEX(Precios!$L$2:$L$100,MATCH($C10,Precios!$A$2:$A$100,0))*INDEX(Precios!$D$2:$D$100,MATCH($C10,Precios!$A$2:$A$100,0))) -> 0.034 | I10: =IFERROR(INDEX(Precios!$L$2:$R$100,MATCH($C10,Precios!$A$2:$A$100,0),MATCH(F10,INDEX(Precios!$E$2:$K$100,MATCH($C10,Precios!$A$2:$A$100,0),0),1))*INDEX(Precios!$D$2:$D$100,MATCH($C10,Precios!$A$2:$A$100,0)),INDEX(Precios!$L$2:$L$100,MATCH($C10,Precios!$A$2:$A$100,0))*INDEX(Precios!$D$2:$D$100,MATCH($C10,Precios!$A$2:$A$100,0))) -> 0.0256 | J10: =IFERROR(INDEX(Precios!$L$2:$R$100,MATCH($C10,Precios!$A$2:$A$100,0),MATCH(G10,INDEX(Precios!$E$2:$K$100,MATCH($C10,Precios!$A$2:$A$100,0),0),1))*INDEX(Precios!$D$2:$D$100,MATCH($C10,Precios!$A$2:$A$100,0)),INDEX(Precios!$L$2:$L$100,MATCH($C10,Precios!$A$2:$A$100,0))*INDEX(Precios!$D$2:$D$100,MATCH($C10,Precios!$A$2:$A$100,0))) -> 0.0256 | K10: =E10*H10 -> 0.68 | L10: =F10*I10 -> 5.12 | M10: =G10*J10 -> 51.2 | N10: =INDEX(Precios!$S$2:$S$100,MATCH($C10,Precios!$A$2:$A$100,0)) -> ESTIMADO (proxy)
A11: =BOM!A11 -> 10 | B11: =BOM!B11 -> R2, R3, R4, R5 | C11: =BOM!J11 -> R_GEN | D11: =IF(BOM!K11="",BOM!D11,BOM!D11*BOM!K11) -> 4 | E11: =D11*Supuestos!$B$2 -> 40 | F11: =D11*Supuestos!$B$3 -> 400 | G11: =D11*Supuestos!$B$4 -> 4000 | H11: =IFERROR(INDEX(Precios!$L$2:$R$100,MATCH($C11,Precios!$A$2:$A$100,0),MATCH(E11,INDEX(Precios!$E$2:$K$100,MATCH($C11,Precios!$A$2:$A$100,0),0),1))*INDEX(Precios!$D$2:$D$100,MATCH($C11,Precios!$A$2:$A$100,0)),INDEX(Precios!$L$2:$L$100,MATCH($C11,Precios!$A$2:$A$100,0))*INDEX(Precios!$D$2:$D$100,MATCH($C11,Precios!$A$2:$A$100,0))) -> 0.0256 | I11: =IFERROR(INDEX(Precios!$L$2:$R$100,MATCH($C11,Precios!$A$2:$A$100,0),MATCH(F11,INDEX(Precios!$E$2:$K$100,MATCH($C11,Precios!$A$2:$A$100,0),0),1))*INDEX(Precios!$D$2:$D$100,MATCH($C11,Precios!$A$2:$A$100,0)),INDEX(Precios!$L$2:$L$100,MATCH($C11,Precios!$A$2:$A$100,0))*INDEX(Precios!$D$2:$D$100,MATCH($C11,Precios!$A$2:$A$100,0))) -> 0.0256 | J11: =IFERROR(INDEX(Precios!$L$2:$R$100,MATCH($C11,Precios!$A$2:$A$100,0),MATCH(G11,INDEX(Precios!$E$2:$K$100,MATCH($C11,Precios!$A$2:$A$100,0),0),1))*INDEX(Precios!$D$2:$D$100,MATCH($C11,Precios!$A$2:$A$100,0)),INDEX(Precios!$L$2:$L$100,MATCH($C11,Precios!$A$2:$A$100,0))*INDEX(Precios!$D$2:$D$100,MATCH($C11,Precios!$A$2:$A$100,0))) -> 0.0256 | K11: =E11*H11 -> 1.024 | L11: =F11*I11 -> 10.24 | M11: =G11*J11 -> 102.4 | N11: =INDEX(Precios!$S$2:$S$100,MATCH($C11,Precios!$A$2:$A$100,0)) -> ESTIMADO (proxy)
A12: =BOM!A12 -> 11 | B12: =BOM!B12 -> C2, C5 | C12: =BOM!J12 -> C_PF | D12: =IF(BOM!K12="",BOM!D12,BOM!D12*BOM!K12) -> 2 | E12: =D12*Supuestos!$B$2 -> 20 | F12: =D12*Supuestos!$B$3 -> 200 | G12: =D12*Supuestos!$B$4 -> 2000 | H12: =IFERROR(INDEX(Precios!$L$2:$R$100,MATCH($C12,Precios!$A$2:$A$100,0),MATCH(E12,INDEX(Precios!$E$2:$K$100,MATCH($C12,Precios!$A$2:$A$100,0),0),1))*INDEX(Precios!$D$2:$D$100,MATCH($C12,Precios!$A$2:$A$100,0)),INDEX(Precios!$L$2:$L$100,MATCH($C12,Precios!$A$2:$A$100,0))*INDEX(Precios!$D$2:$D$100,MATCH($C12,Precios!$A$2:$A$100,0))) -> 0.05 | I12: =IFERROR(INDEX(Precios!$L$2:$R$100,MATCH($C12,Precios!$A$2:$A$100,0),MATCH(F12,INDEX(Precios!$E$2:$K$100,MATCH($C12,Precios!$A$2:$A$100,0),0),1))*INDEX(Precios!$D$2:$D$100,MATCH($C12,Precios!$A$2:$A$100,0)),INDEX(Precios!$L$2:$L$100,MATCH($C12,Precios!$A$2:$A$100,0))*INDEX(Precios!$D$2:$D$100,MATCH($C12,Precios!$A$2:$A$100,0))) -> 0.02 | J12: =IFERROR(INDEX(Precios!$L$2:$R$100,MATCH($C12,Precios!$A$2:$A$100,0),MATCH(G12,INDEX(Precios!$E$2:$K$100,MATCH($C12,Precios!$A$2:$A$100,0),0),1))*INDEX(Precios!$D$2:$D$100,MATCH($C12,Precios!$A$2:$A$100,0)),INDEX(Precios!$L$2:$L$100,MATCH($C12,Precios!$A$2:$A$100,0))*INDEX(Precios!$D$2:$D$100,MATCH($C12,Precios!$A$2:$A$100,0))) -> 0.012 | K12: =E12*H12 -> 1 | L12: =F12*I12 -> 4 | M12: =G12*J12 -> 24 | N12: =INDEX(Precios!$S$2:$S$100,MATCH($C12,Precios!$A$2:$A$100,0)) -> ESTIMADO
A13: =BOM!A13 -> 12 | B13: =BOM!B13 -> C3, C4 | C13: =BOM!J13 -> C_2U2 | D13: =IF(BOM!K13="",BOM!D13,BOM!D13*BOM!K13) -> 2 | E13: =D13*Supuestos!$B$2 -> 20 | F13: =D13*Supuestos!$B$3 -> 200 | G13: =D13*Supuestos!$B$4 -> 2000 | H13: =IFERROR(INDEX(Precios!$L$2:$R$100,MATCH($C13,Precios!$A$2:$A$100,0),MATCH(E13,INDEX(Precios!$E$2:$K$100,MATCH($C13,Precios!$A$2:$A$100,0),0),1))*INDEX(Precios!$D$2:$D$100,MATCH($C13,Precios!$A$2:$A$100,0)),INDEX(Precios!$L$2:$L$100,MATCH($C13,Precios!$A$2:$A$100,0))*INDEX(Precios!$D$2:$D$100,MATCH($C13,Precios!$A$2:$A$100,0))) -> 0.1 | I13: =IFERROR(INDEX(Precios!$L$2:$R$100,MATCH($C13,Precios!$A$2:$A$100,0),MATCH(F13,INDEX(Precios!$E$2:$K$100,MATCH($C13,Precios!$A$2:$A$100,0),0),1))*INDEX(Precios!$D$2:$D$100,MATCH($C13,Precios!$A$2:$A$100,0)),INDEX(Precios!$L$2:$L$100,MATCH($C13,Precios!$A$2:$A$100,0))*INDEX(Precios!$D$2:$D$100,MATCH($C13,Precios!$A$2:$A$100,0))) -> 0.05 | J13: =IFERROR(INDEX(Precios!$L$2:$R$100,MATCH($C13,Precios!$A$2:$A$100,0),MATCH(G13,INDEX(Precios!$E$2:$K$100,MATCH($C13,Precios!$A$2:$A$100,0),0),1))*INDEX(Precios!$D$2:$D$100,MATCH($C13,Precios!$A$2:$A$100,0)),INDEX(Precios!$L$2:$L$100,MATCH($C13,Precios!$A$2:$A$100,0))*INDEX(Precios!$D$2:$D$100,MATCH($C13,Precios!$A$2:$A$100,0))) -> 0.03 | K13: =E13*H13 -> 2 | L13: =F13*I13 -> 10 | M13: =G13*J13 -> 60 | N13: =INDEX(Precios!$S$2:$S$100,MATCH($C13,Precios!$A$2:$A$100,0)) -> ESTIMADO
... A21: =BOM!A21 -> 20 | B21: =BOM!B21 -> P3 (J_TELEM) | C21: =BOM!J21 -> HDR_PIN | D21: =IF(BOM!K21="",BOM!D21,BOM!D21*BOM!K21) -> 4 | E21: =D21*Supuestos!$B$2 -> 40 | F21: =D21*Supuestos!$B$3 -> 400 | G21: =D21*Supuestos!$B$4 -> 4000 | H21: =IFERROR(INDEX(Precios!$L$2:$R$100,MATCH($C21,Precios!$A$2:$A$100,0),MATCH(E21,INDEX(Precios!$E$2:$K$100,MATCH($C21,Precios!$A$2:$A$100,0),0),1))*INDEX(Precios!$D$2:$D$100,MATCH($C21,Precios!$A$2:$A$100,0)),INDEX(Precios!$L$2:$L$100,MATCH($C21,Precios!$A$2:$A$100,0))*INDEX(Precios!$D$2:$D$100,MATCH($C21,Precios!$A$2:$A$100,0))) -> 0.08 | I21: =IFERROR(INDEX(Precios!$L$2:$R$100,MATCH($C21,Precios!$A$2:$A$100,0),MATCH(F21,INDEX(Precios!$E$2:$K$100,MATCH($C21,Precios!$A$2:$A$100,0),0),1))*INDEX(Precios!$D$2:$D$100,MATCH($C21,Precios!$A$2:$A$100,0)),INDEX(Precios!$L$2:$L$100,MATCH($C21,Precios!$A$2:$A$100,0))*INDEX(Precios!$D$2:$D$100,MATCH($C21,Precios!$A$2:$A$100,0))) -> 0.05 | J21: =IFERROR(INDEX(Precios!$L$2:$R$100,MATCH($C21,Precios!$A$2:$A$100,0),MATCH(G21,INDEX(Precios!$E$2:$K$100,MATCH($C21,Precios!$A$2:$A$100,0),0),1))*INDEX(Precios!$D$2:$D$100,MATCH($C21,Precios!$A$2:$A$100,0)),INDEX(Precios!$L$2:$L$100,MATCH($C21,Precios!$A$2:$A$100,0))*INDEX(Precios!$D$2:$D$100,MATCH($C21,Precios!$A$2:$A$100,0))) -> 0.03 | K21: =E21*H21 -> 3.2 | L21: =F21*I21 -> 20 | M21: =G21*J21 -> 120 | N21: =INDEX(Precios!$S$2:$S$100,MATCH($C21,Precios!$A$2:$A$100,0)) -> ESTIMADO
B23: TOTAL lote (USD) | K23: =SUM(K2:K21) -> 230.2879 | L23: =SUM(L2:L21) -> 1961.978 | M23: =SUM(M2:M21) -> 18422.52
B24: Costo por tarjeta (USD) | K24: =K23/Supuestos!$B$2 -> 23.02879 | L24: =L23/Supuestos!$B$3 -> 19.61978 | M24: =M23/Supuestos!$B$4 -> 18.42252
B25: Parte del costo por tarjeta con precio ESTIMADO (%) | K25: =SUMPRODUCT((LEFT($N$2:$N$21,8)="ESTIMADO")*K2:K21)/K23 -> 0.3537485 | L25: =SUMPRODUCT((LEFT($N$2:$N$21,8)="ESTIMADO")*L2:L21)/L23 -> 0.35511611 | M25: =SUMPRODUCT((LEFT($N$2:$N$21,8)="ESTIMADO")*M2:M21)/M23 -> 0.35615649
B28: Tamaño del lote | C28: Costo de componentes del lote (USD) | D28: Costo por tarjeta (USD) | E28: Observaciones
B29: =Supuestos!$B$2 -> 10 | C29: =K23 -> 230.2879 | D29: =K24 -> 23.02879 | E29: Escalón de 10 piezas en los ICs; poco descuento.
B30: =Supuestos!$B$3 -> 100 | C30: =L23 -> 1961.978 | D30: =L24 -> 19.61978 | E30: Se alcanzan escalones de 100+ piezas en los ICs principales.
B31: =Supuestos!$B$4 -> 1000 | C31: =M23 -> 18422.52 | D31: =M24 -> 18.42252 | E31: Se aplica el último escalón publicado cuando la cantidad lo supera (conservador).
B50: Sobrantes: se compra exactamente la cantidad de piezas requeridas (múltiplo de empaque = 1, venta por unidad/cinta cortada). Si el proveedor exige bandeja o carrete completo (p.ej. eMMC bandeja de 152), el costo y los sobrantes cambian.

Sheet Calculos
A1: Cálculo / parámetro | B1: Valor | C1: Unidad | D1: Fuente o nota
A2: 1. Cristal HSE (red de carga)
A3: CL del cristal ABM3B-25.000MHZ-B4U-T | B3: 18 | C3: pF | D3: Valor reportado por un distribuidor (ibselectronics.cn). VERIFICAR con la hoja de datos de Abracon. El informe previo usaba 8 pF, que no corresponde a esta referencia.
A4: C parásita estimada (pista + pines) | B4: 3 | C4: pF | D4: SUPUESTO típico 2-5 pF
A5: C externa requerida por condensador = 2(CL - Cstray) | B5: =2*(B3-B4) -> 30 | C5: pF | D5: Fórmula CL = C1*C2/(C1+C2) + Cstray con C1 = C2
A6: C externa instalada (C2, C5 en el esquemático) | B6: 16 | C6: pF | D6: Esquemático as-built
A7: CL efectiva con C instalada = Cext/2 + Cstray | B7: =B6/2+B4 -> 11 | C7: pF | D7: Con 16 pF resulta menor que el CL del cristal
A8: Desviación de CL (efectiva - requerida) | B8: =B7-B3 -> -7 | C8: pF | D8: Negativa: la frecuencia de oscilación queda ligeramente por encima de la nominal. DESVIACIÓN DOCUMENTADA (ver hoja Desviaciones); corregir a ~30 pF o cambiar el cristal en la siguiente revisión.
A10: 2. Pull-ups I2C
A11: Vcc | B11: 3.3 | C11: V | D11: 3V3_DIGITAL
A12: VOL | B12: 0.4 | C12: V | D12: Especificación I2C
A13: IOL | B13: 0.003 | C13: A | D13: Especificación I2C modo estándar/rápido
A14: tr máximo | B14: 3e-07 | C14: s | D14: Modo rápido (300 ns)
A15: Cb (capacitancia del bus) | B15: 5e-11 | C15: F | D15: SUPUESTO del equipo
A16: Rp mínimo = (Vcc - VOL)/IOL | B16: =(B11-B12)/B13 -> 966.66667 | C16: ohm
A17: Rp máximo = tr/(0,8473 Cb) | B17: =B14/(0.8473*B15) -> 7081.3171 | C17: ohm
A18: Rp adoptado (R6, R7) | B18: 4700 | C18: ohm | D18: Dentro del intervalo [Rp mín, Rp máx]
A19: Verificación | B19: =IF(AND(B18>=B16,B18<=B17),"CUMPLE","NO CUMPLE") -> CUMPLE
A21: 3. Ancho de pista por corriente (IPC-2221, capa externa)
A22: Corriente de diseño por bobina | B22: 1 | C22: A | D22: SUPUESTO. El informe previo estimaba 1,0-1,5 A por eje. La corriente real depende de la resistencia de la bobina y de VM.
A23: Aumento de temperatura admisible | B23: 10 | C23: °C | D23: SUPUESTO
A24: Espesor de cobre | B24: 1 | C24: oz | D24: SUPUESTO preliminar (1 oz = 1,378 mil); falta definir con el apilamiento
A25: k (capa externa) | B25: 0.048 | D25: IPC-2221
A26: Área de sección = (I/(k·ΔT^0,44))^(1/0,725) | B26: =(B22/(B25*B23^0.44))^(1/0.725) -> 16.296001 | C26: mil² | D26: IPC-2221
A27: Ancho mínimo | B27: =B26/(1.378*B24) -> 11.825836 | C27: mil
A28: Ancho mínimo en mm | B28: =B27*0.0254 -> 0.30037622 | C28: mm | D28: Registrar con margen (p.ej. x1,5-2); la caída de tensión y la temperatura final pueden exigir mayor ancho
A29: Ancho con corriente 1,5 A (para comparar) | B29: =((1.5/(B25*B23^0.44))^(1/0.725))/(1.378*B24)*0.0254 -> 0.52547256 | C29: mm
A31: 4. Consumo de la tarjeta (valores heredados del informe)
A32: Corriente digital nominal a 3,3 V | B32: 0.1 | C32: A | D32: Valor del informe previo (estimado; sin verificar con hojas de datos)
A33: Corriente digital pico a 3,3 V | B33: 0.25 | C33: A | D33: Valor del informe previo (estimado; sin verificar con hojas de datos)
A34: Potencia digital nominal | B34: =3.3*B32 -> 0.33 | C34: W | D34: P = V·I
A35: Potencia digital pico | B35: =3.3*B33 -> 0.825 | C35: W | D35: P = V·I
A36: NOTA | D36: El consumo de las bobinas no se calcula porque no se definió su resistencia; queda pendiente. La corriente real del DRV8833 depende de VM, de la bobina y de la limitación del driver.

Sheet Restricciones
A1: ID | B1: Origen (requisito/ET/interfaz) | C1: Restricción y alcance (condición, valor, unidad, redes/componentes) | D1: Tipo | E1: Fuente y fundamento | F1: Aplicación (dónde se registra) | G1: Verificación | H1: Estado
A2: PCB-01 | B2: ET alimentación / MAIN_BUS_POWER | C2: Pista de MAIN_BUS_POWER (J_EPS pin 1) y VM del DRV8833: ancho mínimo según Calculos B28 (≈0,30 mm para 1 A y ≈0,53 mm para 1,5 A, ΔT 10 °C, 1 oz externa); usar >= 1 mm como objetivo de diseño por margen y caída de tensión. Evitar cuellos de botella en vías: mínimo 2 vías 0,3/0,6 mm por transición. | D2: Inferencia + recomendación | E2: IPC-2221 (cálculo en hoja Calculos); corriente supuesta 1 A (informe previo 1-1,5 A). | F2: Regla de ancho en PCB (Design Rule width) por clase de red POWER | G2: Revisión DRC + cálculo; verificar caída de tensión con longitud real | H2: Pendiente de layout
A3: PCB-02 | B3: Dominio ADCS aislado | C3: Dominios DGND y PGND separados galvánicamente. Distancia mínima (creepage/clearance) entre copper de DGND y de PGND en la zona del ISO7741: >= 8 mm de pad a pad en el aislador DW (SOIC-16 ancho) y sin cobre ni planos bajo el aislador en la barrera. | D3: Exigida por componente + recomendación | E3: ISO7741DWR: aislamiento 5000 Vrms (DigiKey/TI). Distancia exacta: hoja de datos TI, sección Package/Insulation Specifications (por confirmar valor numérico). | F3: Regla de clearance entre clases DGND/PGND; nota en esquemático | G3: Medición en layout (DRC + inspección) | H3: Pendiente de layout
A4: PCB-03 | B4: Dominio ADCS aislado | C4: El plano/retorno de PGND no debe cruzar ni solaparse con DGND. Un único punto de conexión no existe (aislamiento total); los retornos de las bobinas vuelven a PGND por el lado del DRV8833. | D4: Recomendación | E4: Práctica estándar de aislamiento galvánico; cambio documentado en el informe, Sección 2.3. | F4: Clases de red / polígonos separados | G4: Inspección de planos | H4: Pendiente de layout
A5: PCB-04 | B5: DRV8833 / J_COIL_X, J_COIL_Y | C5: Pad térmico (PowerPAD) de U4 conectado a PGND con matriz de vías térmicas (mín. 5 vías 0,3 mm de taladro) a plano de PGND. Zona de cobre ampliada alrededor del pad. | D5: Recomendación del fabricante | E5: Hoja de datos DRV8833, sección Layout (PowerPAD) - confirmar número de vías recomendado. | F5: Nota de ubicación en esquemático (textual) | G5: Inspección + simulación térmica opcional | H5: Pendiente de layout
A6: PCB-05 | B6: STM32H753 / alimentación | C6: Un condensador de desacoplamiento de 100 nF por cada par VDD/VSS, a <= 3 mm del pin, con vía directa al plano. El esquemático actual NO incluye estos condensadores (ver Desviaciones D-08); deben añadirse o compensarse con condensadores en la zona de layout. | D6: Exigida por hoja de datos | E6: AN4938 / datasheet STM32H753 (sección Power supply scheme). Cantidad exacta por confirmar. | F6: Nota en esquemático; regla de ubicación en layout | G6: Revisión manual del layout | H6: Desviación abierta
A7: PCB-06 | B7: STM32H753 / VCAP | C7: Condensadores VCAP (C3, C4 de 2,2 uF) lo más cerca posible de los pines VCAP (81, 125), ESR < 100 mohm (cerámico X7R/X5R). | D7: Exigida por hoja de datos | E7: Datasheet STM32H753, sección Power supply scheme (VCAP). Confirmar valor y ESR. | F7: Nota de ubicación | G7: Inspección de layout | H7: Pendiente de layout
A8: PCB-07 | B8: Reloj HSE | C8: Cristal Y1 y condensadores C2, C5 juntos, a <= 5 mm de PH0/PH1; sin pistas de otras señales ni vías bajo el cristal; guarda de GND (DGND) alrededor. | D8: Recomendación del fabricante | E8: AN2867 (Oscillator design guide for STM8/STM32) - confirmar aplicabilidad al H7. | F8: Nota de ubicación | G8: Inspección | H8: Pendiente de layout
A9: PCB-08 | B9: Reloj HSE | C9: Capacitancia de carga CL = 18 pF (a verificar): requiere Cext ≈ 30 pF por lado con Cstray = 3 pF; instalado 16 pF. Desviación abierta. | D9: Exigida por hoja de datos | E9: Hoja de datos ABM3B-25.000MHZ-B4U-T (por confirmar) + Calculos B3-B9. | F9: Esquemático (valores de C2, C5) | G9: Cálculo en hoja Calculos | H9: Desviación abierta
A10: PCB-09 | B10: IF-04 PAYLOAD_SPI | C10: SPI hacia el payload: resistencias serie de 33 ohm (R2-R5) ubicadas cerca del origen (STM32). Longitud de pista < 100 mm si es posible; sin cruces de planos. | D10: Recomendación | E10: Práctica de integridad de señal; impedancia no controlada en esta etapa. | F10: Nota + clase de red SPI | G10: Inspección | H10: Pendiente de layout
A11: PCB-10 | B11: IF-05 TELEMETRY_I2C | C11: Pull-ups de 4,7 kohm (R6, R7) a 3V3_DIGITAL dentro del intervalo [967 ohm; 7,08 kohm]. | D11: Cálculo | E11: Hoja Calculos B16-B19 (especificación I2C). | F11: Valores en esquemático | G11: Cálculo | H11: Cumple
A12: PCB-11 | B12: IF-01 CAMERA_DCMI | C12: Bus DCMI (D0-D7, PCLK, HSYNC, VSYNC): grupo de longitud con diferencia máxima entre D0-D7 y PCLK a definir en la guía de enrutamiento (objetivo preliminar <= 5 mm); referencia continua de plano. | D12: Inferencia (objetivo) | E12: Requisito ET-01 >= 40 MB/s (informe). Valor numérico por derivar de la hoja de datos de la cámara (no disponible en este paquete). | F12: Parameter Set / clase de red DCMI (por crear) | G12: Medición de longitudes en layout | H12: Pendiente (valor por definir)
... A25: FAB-08 | B25: Servicios especiales | C25: Posible necesidad de servicio especial: vía rellena (POFV/via-in-pad) y/o HDI para el FBGA-153 a paso 0,5 mm; impedancia controlada si se exige. Identificado para consultar a JLCPCB. | D25: Inferencia | E25: Guía BGA de JLCPCB. | F25: Nota | G25: Consulta con el proveedor | H25: Pendiente
A27: Tipos de fuente: 'Exigida' = condición impuesta por una hoja de datos o fabricante; 'Recomendación' = práctica adoptada por el equipo; 'Inferencia' = deducción propia del equipo. Los valores marcados 'por confirmar' no se pudieron contrastar con la hoja de datos en esta entrega.

Sheet ERC
A1: Fecha/hora | B1: Hoja | C1: Mensaje(s) | D1: Causa | E1: Acción / resolución | F1: Estado
A2: 27/10/2026 06:03 | B2: Top_Level.SchDoc | C2: [Fatal Error] Missing Harness Type on Signal Harness | D2: Había un tramo de cable de harness suelto fuera del diagrama y Sheet Entries sin Harness Type (TELEMETRY_I2C, PAYLOAD_SPI). | E2: Se asignó el Harness Type correcto a los Sheet Entries y se eliminó el cable suelto. | F2: Resuelto
A3: 27/10/2026 06:03 | B3: U_Interfaces_Connectors / U_OBC_Core | C3: Duplicate Component Designators C5, J1; Duplicate Net Names NetC5_1 | D3: Designadores repetidos entre hojas y eMMC sin anotar ('*'). | E3: Tools > Annotation > Reset All y Annotate Schematics (Across Then Down). | F3: Resuelto
A4: 27/10/2026 06:20 | B4: Top_Level.SchDoc | C4: Duplicate Net Names Wire FMC_SDNE0 | D4: Dos objetos con el mismo nombre en Top_Level. | E4: Corregido en el esquemático. | F4: Resuelto (verificado a las 06:22: ya no aparece)
A5: 27/10/2026 06:22 | B5: U_Mass_Storage.SchDoc | C5: Net CLK/CMD has only one pin; Net FMC_* contains floating input pins / has only one pin (decenas de mensajes) | D5: Las señales FMC, SDIO (y DCMI) llegan hasta U_OBC_Core pero los net labels no están conectados a pines del STM32H753. | E5: NO corregido en esta versión. Se acepta como EXCEPCIÓN DOCUMENTADA: la asignación de pines FMC/SDIO/DCMI se hará en CubeMX y se conectará en la siguiente revisión (Desviación D-01). No se desactivó el ERC globalmente. | F5: Excepción aceptada (abierta)
B6: Revisión manual | C6: Pendiente: revisión cruzada entre ambos integrantes | D6: Debe hacerse y documentarse antes de entregar. | E6: Completar fecha, revisor y observaciones. | F6: PENDIENTE

Sheet Desviaciones
A1: ID | B1: Tema | C1: Especificación / informe previo | D1: Esquemático as-built | E1: Impacto | F1: Acción propuesta (siguiente revisión) | G1: Estado
A2: D-01 | B2: FMC / SDIO / DCMI | C2: STM32 conectado a SDRAM, eMMC y cámara | D2: Net labels sin conexión a pines del STM32H753 | E2: SDRAM, eMMC y cámara sin enlace con el MCU: no funcionan | F2: Asignar pines en STM32CubeMX (SDMMC 4 u 8 bits, FMC SDRAM, DCMI 8 bits) y conectar | G2: Abierta
A3: D-02 | B3: Aislador ISO7741 | C3: Aislar las 4 señales PWM (A1, A2, B1, B2) | D3: ISO7741 tiene 3 canales en una dirección: PWM_B2 no llega al DRV8833 y BIN2 (pin 10) queda sin conexión | E3: Un puente del DRV8833 queda con una entrada flotante; control de la bobina Y incompleto | F3: Cambiar a ISO7740 (4 canales en el mismo sentido) o reasignar canales | G3: Abierta
A4: D-03 | B4: Alimentación del puente H | C4: VBATT 7,4-8,4 V directo al DRV8833; DCP010505BP solo para el lado aislado lógico | D4: VM del DRV8833 y VCC2 del ISO7741 conectados a la etiqueta 5V_ISO; no hay fuente que genere 5V_ISO (DCP010505BP no está en el esquemático); J_EPS (3 pines) no lleva VBATT | E4: El lado aislado no tiene alimentación definida | F4: Añadir DCP010505BP (o fuente equivalente), llevar VBATT al conector y a VM | G4: Abierta
A5: D-04 | B5: IMU | C5: TDK ICM-20948 en la tabla de componentes | D5: No existe en ninguna hoja | E5: Sin sensado de actitud en esta tarjeta | F5: Añadir IMU (I2C/SPI) y asignar pines | G5: Abierta
A6: D-05 | B6: Ejes de actuación | C6: Tres ejes de magnetorquers | D6: Solo COIL_X y COIL_Y (un DRV8833 = 2 puentes H) | E6: Falta eje Z | F6: Añadir segundo DRV8833 y canales de aislamiento, o declarar 2 ejes como simplificación del alcance | G6: Abierta (se declara 2 ejes)
A7: D-06 | B7: Cristal HSE | C7: Informe: CL = 8 pF, C = 12 pF | D7: C2 = C5 = 16 pF; cristal ABM3B-25.000MHZ-B4U-T cuya CL reportada es 18 pF | E7: Posible error de frecuencia/arranque del oscilador | F7: Verificar CL en hoja de datos y recalcular (Cext ≈ 30 pF con Cstray = 3 pF) | G7: Abierta
A8: D-07 | B8: SDRAM | C8: Informe previo: ISSI IS42S16400J-7TL | D8: Micron MT48LC4M16A2P-6A | E8: Informe desactualizado; Last Time Buy vencido (30/06/2026) | F8: Informe corregido para reflejar el esquemático; evaluar alternativa (ISSI o Alliance Memory) | G8: Corregido en informe
A9: D-08 | B9: Desacoplamiento STM32 | C9: Condensador cerámico cerca de cada pin de alimentación | D9: Un solo 100 nF (en NRST); 14 VDD sin condensador dedicado | E9: Riesgo de integridad de alimentación | F9: Añadir 100 nF por par VDD/VSS y 4,7 uF de volumen | G9: Abierta
A10: D-09 | B10: eMMC VCCQ | C10: Informe previo: VCCQ = 1,8 V | D10: VCCQ = 3V3_DIGITAL | E10: El informe se corrigió al esquemático | F10: Mantener 3,3 V si la interfaz del host lo permite | G10: Corregido en informe
A11: D-10 | B11: Puntos de prueba | C11: NRST, VCAP, 3.3V_Iso, PWM | D11: No hay test points en el esquemático | E11: Dificulta la verificación de la tarjeta | F11: Añadir test points | G11: Abierta
A12: D-11 | B12: Pines PWM vs FMC | C12: - | D12: PWM_A1/A2/B1/B2 asignados a PE9, PE11, PE13, PE14, que son pines de datos de FMC | E12: Conflicto al conectar FMC | F12: Reasignar PWM a pines de timer libres en CubeMX | G12: Abierta
... A14: D-13 | B14: Cajetín de hojas | C14: Título, número, revisión y autores | D14: Cajetines vacíos | E14: Falta identificación de las hojas | F14: Rellenar Title, Number, Revision, Drawn By | G14: Abierta
